ask_pydantic/__init__.py
ask_pydantic/_agent.py
ask_pydantic/cli.py
ask_pydantic/data.py
ask_pydantic/db.py
ask_pydantic-0.1.4.dist-info/METADATA
ask_pydantic-0.1.4.dist-info/WHEEL
ask_pydantic-0.1.4.dist-info/entry_points.txt
ask_pydantic-0.1.4.dist-info/top_level.txt
ask_pydantic-0.1.4.dist-info/RECORD
