Metadata-Version: 2.4
Name: ask-pydantic
Version: 0.1.4
Summary: CLI tool to ask questions about Pydantic AI and Logfire documentation
Author-email: David Sanchez <64162682+dsfaccini@users.noreply.github.com>
License-Expression: MIT
Project-URL: Homepage, https://github.com/dsfaccini/ask-pydantic
Project-URL: Repository, https://github.com/dsfaccini/ask-pydantic
Project-URL: Issues, https://github.com/dsfaccini/ask-pydantic/issues
Project-URL: Twitter, https://x.com/dasfacc
Requires-Python: >=3.12
Requires-Dist: bs4>=0.0.2
Requires-Dist: lancedb>=0.25.0
Requires-Dist: langchain-text-splitters>=0.3.11
Requires-Dist: logfire>=4.9.0
Requires-Dist: markdown2>=2.5.4
Requires-Dist: pydantic-ai-slim[anthropic,google,groq,mistral,openai]>=1.0.10
Requires-Dist: python-frontmatter>=1.1.0
Requires-Dist: questionary>=2.0.0
Requires-Dist: sentence-transformers>=5.1.1
